LICENSE.txt
MANIFEST.in
README.rst
setup.cfg
setup.py
h2tools/__init__.py
h2tools/__version__.py
h2tools/cluster_tree.py
h2tools/h2matrix.py
h2tools/mcbh.py
h2tools/minimal_data.py
h2tools/mpi_misc.py
h2tools/problem.py
h2tools/setup.py
h2tools.egg-info/PKG-INFO
h2tools.egg-info/SOURCES.txt
h2tools.egg-info/dependency_links.txt
h2tools.egg-info/requires.txt
h2tools.egg-info/top_level.txt
h2tools/collections/__init__.py
h2tools/collections/integral.py
h2tools/collections/particles.py
h2tools/collections/pcm.py
h2tools/collections/setup.py
h2tools/collections/triangular_surface.py