Metadata-Version: 1.0
Name: h2tools
Version: 1.1.1
Summary: About `h2tools`.
Home-page: https://bitbucket.org/muxas/h2tools
Author: Alexander Mikhalev
Author-email: muxasizhevsk@gmail.com
License: MIT
Platform: UNKNOWN
